my_number_sorter/__init__.py
my_number_sorter/sorter.py
my_number_sorter-0.2.dist-info/METADATA
my_number_sorter-0.2.dist-info/WHEEL
my_number_sorter-0.2.dist-info/top_level.txt
my_number_sorter-0.2.dist-info/RECORD
