Metadata-Version: 2.1
Name: my_number_sorter
Version: 0.2
Summary: # My Number Sorter
Author: Adedotun
Author-email: adedotunabimbola2@gmail.com
Classifier: Programming Language :: Python :: 3
Classifier: License :: OSI Approved :: MIT License
Classifier: Operating System :: OS Independent
Requires-Python: >=3.6
